pavo/.pavo.default.toml
pavo/__init__.py
pavo/__main__.py
pavo/_types.py
pavo/_version.py
pavo/app.py
pavo/cli.py
pavo/config.py
pavo/data.py
pavo/extensions.py
pavo/utils.py
pavo/worker.py
pavo/api/__init__.py
pavo/api/api.py
pavo/api/utils.py
pavo/home/__init__.py
pavo/home/tasks.py
pavo/home/views.py
pavo/metadata/__init__.py
pavo/metadata/utils.py
pavo/metadata/views.py
pavo/slides/__init__.py
pavo/slides/cache.py
pavo/slides/tasks.py
pavo/slides/utils.py
pavo/slides/views.py
pavo/static/_base.css
pavo/static/_base.js
pavo/static/home.css
pavo/static/home.js
pavo/static/metadata.css
pavo/static/metadata.js
pavo/static/metadata.js.LICENSE.txt
pavo/static/slides.css
pavo/static/slides.js
pavo/static/slides_deckgl.css
pavo/static/slides_deckgl.js
pavo/static/slides_deckgl.js.LICENSE.txt
pavo/static/slides_openseadragon.css
pavo/static/slides_openseadragon.js
pavo/static/slides_openseadragon.js.LICENSE.txt
pavo/static/fonts/3683f6a94b5f8296e52c.ttf
pavo/static/fonts/45e5578c8bbd9983075e.eot
pavo/static/fonts/aca594e75dff247ef638.svg
pavo/static/fonts/f336d59933210dafd082.woff
pavo/static/fonts/fa-solid-900.eot
pavo/static/fonts/fa-solid-900.svg
pavo/static/fonts/fa-solid-900.ttf
pavo/static/fonts/fa-solid-900.woff
pavo/static/fonts/fa-solid-900.woff2
pavo/static/images/background_landing.jpg
pavo/static/images/pathological-heart.jpg
pavo/static/images/openseadragon/button_grouphover.png
pavo/static/images/openseadragon/button_hover.png
pavo/static/images/openseadragon/button_pressed.png
pavo/static/images/openseadragon/button_rest.png
pavo/static/images/openseadragon/flip_grouphover.png
pavo/static/images/openseadragon/flip_hover.png
pavo/static/images/openseadragon/flip_pressed.png
pavo/static/images/openseadragon/flip_rest.png
pavo/static/images/openseadragon/fullpage_grouphover.png
pavo/static/images/openseadragon/fullpage_hover.png
pavo/static/images/openseadragon/fullpage_pressed.png
pavo/static/images/openseadragon/fullpage_rest.png
pavo-0.3.0.dist-info/LICENSE
pavo-0.3.0.dist-info/METADATA
pavo-0.3.0.dist-info/WHEEL
pavo-0.3.0.dist-info/entry_points.txt
pavo-0.3.0.dist-info/top_level.txt
pavo-0.3.0.dist-info/RECORD
