Metadata-Version: 2.1
Name: pavo
Version: 0.3.0
Summary: PAthological Visualisation Obsession
Home-page: https://github.com/bayer-group/pavo
Download-URL: https://github.com/bayer-group/pavo
Author: Andreas Poehlmann
Author-email: andreas.poehlmann@bayer.com
License: BSD
Classifier: Development Status :: 3 - Alpha
Classifier: Intended Audience :: Science/Research
Classifier: License :: OSI Approved :: BSD License
Classifier: Programming Language :: Python
Classifier: Programming Language :: Python :: 3 :: Only
Classifier: Programming Language :: Python :: 3.8
Classifier: Programming Language :: Python :: 3.9
Classifier: Programming Language :: Python :: 3.10
Classifier: Programming Language :: Python :: 3.11
Classifier: Topic :: Scientific/Engineering
Classifier: Topic :: Scientific/Engineering :: Information Analysis
Classifier: Topic :: Scientific/Engineering :: Bio-Informatics
Classifier: Topic :: Utilities
Classifier: Operating System :: Microsoft :: Windows
Classifier: Operating System :: POSIX
Classifier: Operating System :: Unix
Classifier: Operating System :: MacOS
Requires-Python: >=3.8
License-File: LICENSE
Requires-Dist: celery
Requires-Dist: click
Requires-Dist: dynaconf
Requires-Dist: filelock
Requires-Dist: flask-caching (>=1.8.0)
Requires-Dist: flask (>=2)
Requires-Dist: fsspec
Requires-Dist: geopandas
Requires-Dist: importlib-resources
Requires-Dist: itsdangerous
Requires-Dist: orjson
Requires-Dist: pado (>=0.12)
Requires-Dist: pandas
Requires-Dist: pillow
Requires-Dist: redis
Requires-Dist: tiffslide (>=2)
Requires-Dist: tqdm
Requires-Dist: typer
Requires-Dist: typing-extensions
Requires-Dist: werkzeug
Provides-Extra: dev
Requires-Dist: pre-commit ; extra == 'dev'
Requires-Dist: black ; extra == 'dev'
Requires-Dist: pytest (>=6) ; extra == 'dev'
Requires-Dist: pytest-cov ; extra == 'dev'
Requires-Dist: mypy ; extra == 'dev'
